<xml xmlns:o="urn:schemas-microsoft-com:office:office">
 <o:MainFile HRef="../relatorio.html"/>
 <o:File HRef="Pasta1_4877_image001.png" PublicationID="Pasta1_4877"/>
 <o:File HRef="Pasta1_4877_image002.png" PublicationID="Pasta1_4877"/>
 <o:File HRef="Pasta1_4877_image003.png" PublicationID="Pasta1_4877"/>
 <o:File HRef="Pasta1_4877_image004.png" PublicationID="Pasta1_4877"/>
 <o:File HRef="Pasta1_4877_image005.png" PublicationID="Pasta1_4877"/>
 <o:File HRef="Pasta1_4877_image006.png" PublicationID="Pasta1_4877"/>
 <o:File HRef="Pasta1_4877_image007.png" PublicationID="Pasta1_4877"/>
 <o:File HRef="Pasta1_4877_image008.png" PublicationID="Pasta1_4877"/>
 <o:File HRef="Pasta1_4877_image009.png" PublicationID="Pasta1_4877"/>
 <o:File HRef="Pasta1_4877_image010.png" PublicationID="Pasta1_4877"/>
 <o:File HRef="Pasta1_4877_image011.png" PublicationID="Pasta1_4877"/>
 <o:File HRef="Pasta1_4877_image012.png" PublicationID="Pasta1_4877"/>
 <o:File HRef="Pasta1_4877_image013.png" PublicationID="Pasta1_4877"/>
 <o:File HRef="Pasta1_4877_image014.png" PublicationID="Pasta1_4877"/>
 <o:File HRef="Pasta1_4877_image015.png" PublicationID="Pasta1_4877"/>
 <o:File HRef="Pasta1_4877_image016.png" PublicationID="Pasta1_4877"/>
 <o:File HRef="Pasta1_4877_image017.png" PublicationID="Pasta1_4877"/>
 <o:File HRef="filelist.xml"/>
</xml>